{
  "title": "광화문광장 간 김규리 “BTS 너무나 자랑스러워” [IS하이컷] - v.daum.net",
  "link": "https://news.google.com/rss/articles/CBMiT0FVX3lxTE9idE00MUt0UHdWRnZXNDNzb19iVFNGTnA1UkZUbWNlMXN6T3VtdDVfS1VVcU85a1RDMmk0OThZS0dzejNvMDBLUEZIem1BMkU?oc=5",
  "pubDate": "Sat, 21 Mar 2026 04:46:25 GMT",
  "source": "v.daum.net",
  "sourceType": "news",
  "description": "",
  "severity": "medium",
  "tags": [
    "BTS 광화문 콘서트",
    "뉴스"
  ],
  "imageUrl": "",
  "thumbnailUrl": "",
  "collectedAt": "2026-03-21T05:16:33.791Z"
}