{
  "title": "[BTS 콘서트]어린이부터 6070까지 \"보라해\"…'컴백' BTS에 광화문은 축제 중 - 네이트",
  "link": "https://news.google.com/rss/articles/CBMiU0FVX3lxTE5KM0tnbWNpRGlVQXU5ZW5wVTRsOEktVHdDVFJtQWw1amY5eUNnS3F6cU1EUzNRZkQyTEZDbEtfMHB0TkV2QUM4YS1xcVdjUlcybTAw?oc=5",
  "pubDate": "Sat, 21 Mar 2026 09:01:00 GMT",
  "source": "네이트",
  "sourceType": "news",
  "description": "",
  "severity": "medium",
  "tags": [
    "BTS 광화문 콘서트",
    "뉴스"
  ],
  "imageUrl": "",
  "thumbnailUrl": "",
  "collectedAt": "2026-03-21T09:16:10.410Z"
}