{
  "title": "대전 공장 화재, 실종자 1명 숨진 채 발견...야간 수색 계속 - 뉴스토마토",
  "link": "https://news.google.com/rss/articles/CBMiYEFVX3lxTE8yNEowY3BFeHpWNUtsdng5bGdMaEFVVzFiZnN6azFqVzAwSHJ4T01LelhGOExYWVZ1UGkxR2JrOTdwQTJlM3MzU1pWQlBBN3E0dElJTEh0X1JOcHRRclhfVQ?oc=5",
  "pubDate": "Fri, 20 Mar 2026 16:59:57 GMT",
  "source": "뉴스토마토",
  "sourceType": "news",
  "description": "",
  "severity": "medium",
  "tags": [
    "대전 화재",
    "뉴스"
  ],
  "imageUrl": "",
  "thumbnailUrl": "",
  "collectedAt": "2026-03-20T18:00:49.404Z"
}