{
  "title": "[속보] 대전 화재현장서 마지막 실종자 시신 3구 추가 수습...실종자 14명 전원 확인 - 경기일보",
  "link": "https://news.google.com/rss/articles/CBMiW0FVX3lxTFBxczk4WHh0WkpxV3BrQVpuM05ZWjMtUjdiTEVsSGtVa0FVMEs2WnVoYjRiSkpLR2dqV3NvQXVCdVZ2NlQxTlVvNEg1VTQ5ZEFwLXU2Wl9RMWdGbTg?oc=5",
  "pubDate": "Sat, 21 Mar 2026 08:32:00 GMT",
  "source": "경기일보",
  "sourceType": "news",
  "description": "",
  "severity": "medium",
  "tags": [
    "대전 화재",
    "뉴스"
  ],
  "imageUrl": "",
  "thumbnailUrl": "",
  "collectedAt": "2026-03-21T09:15:44.540Z"
}